{
  "id": "iron_sword",
  "width": 32,
  "height": 32,
  "palette": {
    ".": "transparent",
    "a": "#4f3219",
    "b": "#7b5430",
    "c": "#b78750",
    "d": "#4f5963",
    "e": "#97a3ae",
    "f": "#e2e8ef",
    "g": "#bf8c54",
    "h": "#f0c994"
  },
  "pixels": [
    "................................",
    "................................",
    "................................",
    "................................",
    ".......................edf......",
    "......................eeed......",
    ".....................efed.......",
    "....................effd........",
    "...................effd.........",
    "..................effd..........",
    ".................effd...........",
    "................effd............",
    "...............effd.............",
    "..........g...effd..............",
    "...........h.effd...............",
    "............heed................",
    "............dhd.................",
    "..........cb.dh.................",
    ".........ccb...g................",
    "........ccba....................",
    "........bba.....................",
    ".......caa......................",
    "................................",
    "................................",
    "................................",
    "................................",
    "................................",
    "................................",
    "................................",
    "................................",
    "................................",
    "................................"
  ],
  "model": {
    "depth": 4,
    "scale": 0.05,
    "groundVariant": "copy"
  }
}
