{
  "id": "shrimp",
  "width": 32,
  "height": 32,
  "palette": {
    "a": "#965667",
    "b": "#c97f92",
    "c": "#f3c1cb",
    "d": "#ffe1e7",
    "e": "#2b171d",
    ".": "transparent"
  },
  "pixels": [
    "................................",
    "................................",
    "................................",
    "................................",
    "................................",
    "................................",
    "................................",
    "................................",
    "................................",
    "..............d.................",
    "............ddbb................",
    "..........ddbbcccbb.............",
    "........dabbccccccbbb...........",
    "......ddbbccccccccccbbad........",
    ".....abbceccccccccccbbbad.......",
    "......abbccccccccccccbbad.......",
    ".......dabbccccccccccbbad.......",
    ".........abbccccccccbbad........",
    "..........aabbccccbba...........",
    "............aabbbba.............",
    "..............aaa...............",
    "................................",
    "................................",
    "................................",
    "................................",
    "................................",
    "................................",
    "................................",
    "................................",
    "................................",
    "................................",
    "................................"
  ],
  "model": {
    "depth": 4,
    "scale": 0.05,
    "groundVariant": "copy"
  }
}
