{
  "id": "small_pouch",
  "width": 32,
  "height": 32,
  "palette": {
    "0": "#7a5a3a",
    "1": "#9b744b",
    "2": "#5d422a",
    ".": "transparent"
  },
  "pixels": [
    "................................",
    "................................",
    "................................",
    "................................",
    "................................",
    "................................",
    "..........222222222222..........",
    "..........222222222222..........",
    "........0000000000000000........",
    "........0000000000000000........",
    "........0011111111111100........",
    "........0011111111111100........",
    "........0011111111111100........",
    "........0011111111111100........",
    "........0011111111111100........",
    "........0011111111111100........",
    "........0011111111111100........",
    "........0011111111111100........",
    "........0011111111111100........",
    "........0011111111111100........",
    "........0011111111111100........",
    "........0011111111111100........",
    "........0011111111111100........",
    "........0011111111111100........",
    "........0000000000000000........",
    "........0000000000000000........",
    "................................",
    "................................",
    "................................",
    "................................",
    "................................",
    "................................"
  ],
  "model": {
    "depth": 4,
    "scale": 0.05,
    "groundVariant": "copy"
  }
}
