{
  "id": "willow_shafts",
  "width": 32,
  "height": 32,
  "palette": {
    ".": "transparent",
    "a": "#3a2b18",
    "b": "#5d4826",
    "c": "#7b6235",
    "d": "#9a7a46"
  },
  "pixels": [
    "................................",
    "................................",
    "................................",
    "................................",
    "................................",
    "................................",
    "................................",
    "................................",
    "................................",
    "......................a.........",
    "....................ba.cb.......",
    "...................badcb.d......",
    "..................badcb.d.......",
    ".................badcb.d........",
    "................badcb.d.........",
    "...............badcb.d..........",
    "..............badcb.d...........",
    ".............badcb.d............",
    "............babcb.d.............",
    "...........badccdd..............",
    "..........badcb.d...............",
    ".........badcb.d................",
    "........badcb.d.................",
    ".......badcb.d..................",
    "......b.dcb.d...................",
    ".......d...d....................",
    "................................",
    "................................",
    "................................",
    "................................",
    "................................",
    "................................"
  ],
  "model": {
    "depth": 3,
    "scale": 0.05,
    "groundVariant": "copy"
  }
}
